{
  "resources": [
    {
      "path": "data.csv",
      "name": "data",
      "profile": "tabular-data-resource",
      "scheme": "file",
      "format": "csv",
      "hashing": "md5",
      "encoding": "utf-8",
      "schema": {
        "fields": [
          {
            "name": "Year",
            "type": "integer",
            "title": "Year"
          },
          {
            "name": "Units",
            "type": "string",
            "constraints": {
              "enum": [
                "Percentage (%)",
                ""
              ]
            },
            "title": "Units"
          },
          {
            "name": "Unit multiplier",
            "type": "string",
            "title": "Unit multiplier"
          },
          {
            "name": "Observation status",
            "type": "string",
            "title": "Observation status"
          },
          {
            "name": "Value",
            "type": "number",
            "title": "Value"
          }
        ]
      }
    }
  ],
  "profile": "data-package",
  "name": "10-4-1",
  "title": "Labour share of GDP"
}