{"indicator_name":"Mountain Green Cover Index","target_name":"By 2030, ensure the conservation of mountain ecosystems, including their biodiversity, in order to enhance their capacity to provide benefits that are essential for sustainable development","indicator_number":"15.4.2","csv_size":"0.149 kB","un_designated_tier":"Tier I","un_custodian_agency":"Food and Agriculture Organization (FAO)","goal_meta_link":"https://unstats.un.org/sdgs/metadata/?Text=&Goal=15&Target=15.4","goal_meta_link_text":"United Nations Sustainable Development Goals metadata for target 15.4","reporting_status":"notstarted","data_non_statistical":false,"graph_type":"line","data_keywords":null,"expected_disaggregations":null,"source_active_1":false,"source_active_2":false,"source_active_3":false,"source_active_4":false,"source_active_5":false,"source_active_6":false,"indicator_sort_order":"01-03-01","other_info":null,"page_content":"","national_metadata_updated_date":"2021-07-19","national_data_updated_date":"2021-07-19","national_metadata_update_url_text":"2021-07-19: see changes on GitHub","national_metadata_update_url":"https://github.com/ONSdigital/sdg-data/commit/e2c89140f3fae103df0b0fb6c89da9e21ec690d5","national_data_update_url_text":"2021-07-19: see changes on GitHub","national_data_update_url":"https://github.com/ONSdigital/sdg-data/commit/e2c89140f3fae103df0b0fb6c89da9e21ec690d5","indicator":"15.4.2","target_id":"15.4","sdg_goal":"15","graph_title":"Mountain Green Cover Index"}