{"statuses": [{"value": "complete", "translation_key": "status.disaggregation_status_complete"}, {"value": "inprogress", "translation_key": "status.disaggregation_status_inprogress"}, {"value": "notstarted", "translation_key": "status.disaggregation_status_notstarted"}, {"value": "notapplicable", "translation_key": "status.disaggregation_status_notapplicable"}], "overall": {"statuses": [{"status": "complete", "translation_key": "status.disaggregation_status_complete", "count": 19, "percentage": 7.786885245901639}, {"status": "inprogress", "translation_key": "status.disaggregation_status_inprogress", "count": 9, "percentage": 3.6885245901639343}, {"status": "notstarted", "translation_key": "status.disaggregation_status_notstarted", "count": 22, "percentage": 9.01639344262295}, {"status": "notapplicable", "translation_key": "status.disaggregation_status_notapplicable", "count": 194, "percentage": 79.50819672131148}], "totals": {"total": 244}}, "goals": [{"goal": 1, "statuses": [{"status": "complete", "translation_key": "status.disaggregation_status_complete", "count": 1, "percentage": 7.142857142857143}, {"status": "inprogress", "translation_key": "status.disaggregation_status_inprogress", "count": 0, "percentage": 0.0}, {"status": "notstarted", "translation_key": "status.disaggregation_status_notstarted", "count": 3, "percentage": 21.428571428571427}, {"status": "notapplicable", "translation_key": "status.disaggregation_status_notapplicable", "count": 10, "percentage": 71.42857142857143}], "totals": {"total": 14}}, {"goal": 2, "statuses": [{"status": "complete", "translation_key": "status.disaggregation_status_complete", "count": 1, "percentage": 7.6923076923076925}, {"status": "inprogress", "translation_key": "status.disaggregation_status_inprogress", "count": 1, "percentage": 7.6923076923076925}, {"status": "notstarted", "translation_key": "status.disaggregation_status_notstarted", "count": 1, "percentage": 7.6923076923076925}, {"status": "notapplicable", "translation_key": "status.disaggregation_status_notapplicable", "count": 10, "percentage": 76.92307692307692}], "totals": {"total": 13}}, {"goal": 3, "statuses": [{"status": "complete", "translation_key": "status.disaggregation_status_complete", "count": 0, "percentage": 0.0}, {"status": "inprogress", "translation_key": "status.disaggregation_status_inprogress", "count": 1, "percentage": 3.7037037037037037}, {"status": "notstarted", "translation_key": "status.disaggregation_status_notstarted", "count": 0, "percentage": 0.0}, {"status": "notapplicable", "translation_key": "status.disaggregation_status_notapplicable", "count": 26, "percentage": 96.29629629629629}], "totals": {"total": 27}}, {"goal": 4, "statuses": [{"status": "complete", "translation_key": "status.disaggregation_status_complete", "count": 5, "percentage": 45.45454545454545}, {"status": "inprogress", "translation_key": "status.disaggregation_status_inprogress", "count": 0, "percentage": 0.0}, {"status": "notstarted", "translation_key": "status.disaggregation_status_notstarted", "count": 2, "percentage": 18.181818181818183}, {"status": "notapplicable", "translation_key": "status.disaggregation_status_notapplicable", "count": 4, "percentage": 36.36363636363637}], "totals": {"total": 11}}, {"goal": 5, "statuses": [{"status": "complete", "translation_key": "status.disaggregation_status_complete", "count": 4, "percentage": 28.571428571428573}, {"status": "inprogress", "translation_key": "status.disaggregation_status_inprogress", "count": 1, "percentage": 7.142857142857143}, {"status": "notstarted", "translation_key": "status.disaggregation_status_notstarted", "count": 1, "percentage": 7.142857142857143}, {"status": "notapplicable", "translation_key": "status.disaggregation_status_notapplicable", "count": 8, "percentage": 57.142857142857146}], "totals": {"total": 14}}, {"goal": 6, "statuses": [{"status": "complete", "translation_key": "status.disaggregation_status_complete", "count": 0, "percentage": 0.0}, {"status": "inprogress", "translation_key": "status.disaggregation_status_inprogress", "count": 0, "percentage": 0.0}, {"status": "notstarted", "translation_key": "status.disaggregation_status_notstarted", "count": 0, "percentage": 0.0}, {"status": "notapplicable", "translation_key": "status.disaggregation_status_notapplicable", "count": 11, "percentage": 100.0}], "totals": {"total": 11}}, {"goal": 7, "statuses": [{"status": "complete", "translation_key": "status.disaggregation_status_complete", "count": 0, "percentage": 0.0}, {"status": "inprogress", "translation_key": "status.disaggregation_status_inprogress", "count": 0, "percentage": 0.0}, {"status": "notstarted", "translation_key": "status.disaggregation_status_notstarted", "count": 0, "percentage": 0.0}, {"status": "notapplicable", "translation_key": "status.disaggregation_status_notapplicable", "count": 6, "percentage": 100.0}], "totals": {"total": 6}}, {"goal": 8, "statuses": [{"status": "complete", "translation_key": "status.disaggregation_status_complete", "count": 3, "percentage": 17.647058823529413}, {"status": "inprogress", "translation_key": "status.disaggregation_status_inprogress", "count": 1, "percentage": 5.882352941176471}, {"status": "notstarted", "translation_key": "status.disaggregation_status_notstarted", "count": 2, "percentage": 11.764705882352942}, {"status": "notapplicable", "translation_key": "status.disaggregation_status_notapplicable", "count": 11, "percentage": 64.70588235294117}], "totals": {"total": 17}}, {"goal": 9, "statuses": [{"status": "complete", "translation_key": "status.disaggregation_status_complete", "count": 1, "percentage": 8.333333333333334}, {"status": "inprogress", "translation_key": "status.disaggregation_status_inprogress", "count": 0, "percentage": 0.0}, {"status": "notstarted", "translation_key": "status.disaggregation_status_notstarted", "count": 1, "percentage": 8.333333333333334}, {"status": "notapplicable", "translation_key": "status.disaggregation_status_notapplicable", "count": 10, "percentage": 83.33333333333333}], "totals": {"total": 12}}, {"goal": 10, "statuses": [{"status": "complete", "translation_key": "status.disaggregation_status_complete", "count": 0, "percentage": 0.0}, {"status": "inprogress", "translation_key": "status.disaggregation_status_inprogress", "count": 2, "percentage": 18.181818181818183}, {"status": "notstarted", "translation_key": "status.disaggregation_status_notstarted", "count": 0, "percentage": 0.0}, {"status": "notapplicable", "translation_key": "status.disaggregation_status_notapplicable", "count": 9, "percentage": 81.81818181818181}], "totals": {"total": 11}}, {"goal": 11, "statuses": [{"status": "complete", "translation_key": "status.disaggregation_status_complete", "count": 0, "percentage": 0.0}, {"status": "inprogress", "translation_key": "status.disaggregation_status_inprogress", "count": 1, "percentage": 6.666666666666667}, {"status": "notstarted", "translation_key": "status.disaggregation_status_notstarted", "count": 5, "percentage": 33.333333333333336}, {"status": "notapplicable", "translation_key": "status.disaggregation_status_notapplicable", "count": 9, "percentage": 60.0}], "totals": {"total": 15}}, {"goal": 12, "statuses": [{"status": "complete", "translation_key": "status.disaggregation_status_complete", "count": 0, "percentage": 0.0}, {"status": "inprogress", "translation_key": "status.disaggregation_status_inprogress", "count": 1, "percentage": 7.6923076923076925}, {"status": "notstarted", "translation_key": "status.disaggregation_status_notstarted", "count": 0, "percentage": 0.0}, {"status": "notapplicable", "translation_key": "status.disaggregation_status_notapplicable", "count": 12, "percentage": 92.3076923076923}], "totals": {"total": 13}}, {"goal": 13, "statuses": [{"status": "complete", "translation_key": "status.disaggregation_status_complete", "count": 0, "percentage": 0.0}, {"status": "inprogress", "translation_key": "status.disaggregation_status_inprogress", "count": 0, "percentage": 0.0}, {"status": "notstarted", "translation_key": "status.disaggregation_status_notstarted", "count": 0, "percentage": 0.0}, {"status": "notapplicable", "translation_key": "status.disaggregation_status_notapplicable", "count": 8, "percentage": 100.0}], "totals": {"total": 8}}, {"goal": 14, "statuses": [{"status": "complete", "translation_key": "status.disaggregation_status_complete", "count": 0, "percentage": 0.0}, {"status": "inprogress", "translation_key": "status.disaggregation_status_inprogress", "count": 0, "percentage": 0.0}, {"status": "notstarted", "translation_key": "status.disaggregation_status_notstarted", "count": 0, "percentage": 0.0}, {"status": "notapplicable", "translation_key": "status.disaggregation_status_notapplicable", "count": 10, "percentage": 100.0}], "totals": {"total": 10}}, {"goal": 15, "statuses": [{"status": "complete", "translation_key": "status.disaggregation_status_complete", "count": 0, "percentage": 0.0}, {"status": "inprogress", "translation_key": "status.disaggregation_status_inprogress", "count": 0, "percentage": 0.0}, {"status": "notstarted", "translation_key": "status.disaggregation_status_notstarted", "count": 1, "percentage": 7.142857142857143}, {"status": "notapplicable", "translation_key": "status.disaggregation_status_notapplicable", "count": 13, "percentage": 92.85714285714286}], "totals": {"total": 14}}, {"goal": 16, "statuses": [{"status": "complete", "translation_key": "status.disaggregation_status_complete", "count": 2, "percentage": 8.695652173913043}, {"status": "inprogress", "translation_key": "status.disaggregation_status_inprogress", "count": 1, "percentage": 4.3478260869565215}, {"status": "notstarted", "translation_key": "status.disaggregation_status_notstarted", "count": 4, "percentage": 17.391304347826086}, {"status": "notapplicable", "translation_key": "status.disaggregation_status_notapplicable", "count": 16, "percentage": 69.56521739130434}], "totals": {"total": 23}}, {"goal": 17, "statuses": [{"status": "complete", "translation_key": "status.disaggregation_status_complete", "count": 2, "percentage": 8.0}, {"status": "inprogress", "translation_key": "status.disaggregation_status_inprogress", "count": 0, "percentage": 0.0}, {"status": "notstarted", "translation_key": "status.disaggregation_status_notstarted", "count": 2, "percentage": 8.0}, {"status": "notapplicable", "translation_key": "status.disaggregation_status_notapplicable", "count": 21, "percentage": 84.0}], "totals": {"total": 25}}], "extra_fields": {"sdg_goal": [{"sdg_goal": "5", "statuses": [{"status": "complete", "translation_key": "status.disaggregation_status_complete", "count": 4, "percentage": 28.571428571428573}, {"status": "inprogress", "translation_key": "status.disaggregation_status_inprogress", "count": 1, "percentage": 7.142857142857143}, {"status": "notstarted", "translation_key": "status.disaggregation_status_notstarted", "count": 1, "percentage": 7.142857142857143}, {"status": "notapplicable", "translation_key": "status.disaggregation_status_notapplicable", "count": 8, "percentage": 57.142857142857146}], "totals": {"total": 14}}, {"sdg_goal": "1", "statuses": [{"status": "complete", "translation_key": "status.disaggregation_status_complete", "count": 1, "percentage": 7.142857142857143}, {"status": "inprogress", "translation_key": "status.disaggregation_status_inprogress", "count": 0, "percentage": 0.0}, {"status": "notstarted", "translation_key": "status.disaggregation_status_notstarted", "count": 3, "percentage": 21.428571428571427}, {"status": "notapplicable", "translation_key": "status.disaggregation_status_notapplicable", "count": 10, "percentage": 71.42857142857143}], "totals": {"total": 14}}, {"sdg_goal": "17", "statuses": [{"status": "complete", "translation_key": "status.disaggregation_status_complete", "count": 2, "percentage": 8.0}, {"status": "inprogress", "translation_key": "status.disaggregation_status_inprogress", "count": 0, "percentage": 0.0}, {"status": "notstarted", "translation_key": "status.disaggregation_status_notstarted", "count": 2, "percentage": 8.0}, {"status": "notapplicable", "translation_key": "status.disaggregation_status_notapplicable", "count": 21, "percentage": 84.0}], "totals": {"total": 25}}, {"sdg_goal": "14", "statuses": [{"status": "complete", "translation_key": "status.disaggregation_status_complete", "count": 0, "percentage": 0.0}, {"status": "inprogress", "translation_key": "status.disaggregation_status_inprogress", "count": 0, "percentage": 0.0}, {"status": "notstarted", "translation_key": "status.disaggregation_status_notstarted", "count": 0, "percentage": 0.0}, {"status": "notapplicable", "translation_key": "status.disaggregation_status_notapplicable", "count": 10, "percentage": 100.0}], "totals": {"total": 10}}, {"sdg_goal": "10", "statuses": [{"status": "complete", "translation_key": "status.disaggregation_status_complete", "count": 0, "percentage": 0.0}, {"status": "inprogress", "translation_key": "status.disaggregation_status_inprogress", "count": 2, "percentage": 18.181818181818183}, {"status": "notstarted", "translation_key": "status.disaggregation_status_notstarted", "count": 0, "percentage": 0.0}, {"status": "notapplicable", "translation_key": "status.disaggregation_status_notapplicable", "count": 9, "percentage": 81.81818181818181}], "totals": {"total": 11}}, {"sdg_goal": "2", "statuses": [{"status": "complete", "translation_key": "status.disaggregation_status_complete", "count": 1, "percentage": 7.6923076923076925}, {"status": "inprogress", "translation_key": "status.disaggregation_status_inprogress", "count": 1, "percentage": 7.6923076923076925}, {"status": "notstarted", "translation_key": "status.disaggregation_status_notstarted", "count": 1, "percentage": 7.6923076923076925}, {"status": "notapplicable", "translation_key": "status.disaggregation_status_notapplicable", "count": 10, "percentage": 76.92307692307692}], "totals": {"total": 13}}, {"sdg_goal": "11", "statuses": [{"status": "complete", "translation_key": "status.disaggregation_status_complete", "count": 0, "percentage": 0.0}, {"status": "inprogress", "translation_key": "status.disaggregation_status_inprogress", "count": 1, "percentage": 6.666666666666667}, {"status": "notstarted", "translation_key": "status.disaggregation_status_notstarted", "count": 5, "percentage": 33.333333333333336}, {"status": "notapplicable", "translation_key": "status.disaggregation_status_notapplicable", "count": 9, "percentage": 60.0}], "totals": {"total": 15}}, {"sdg_goal": "12", "statuses": [{"status": "complete", "translation_key": "status.disaggregation_status_complete", "count": 0, "percentage": 0.0}, {"status": "inprogress", "translation_key": "status.disaggregation_status_inprogress", "count": 1, "percentage": 7.6923076923076925}, {"status": "notstarted", "translation_key": "status.disaggregation_status_notstarted", "count": 0, "percentage": 0.0}, {"status": "notapplicable", "translation_key": "status.disaggregation_status_notapplicable", "count": 12, "percentage": 92.3076923076923}], "totals": {"total": 13}}, {"sdg_goal": "6", "statuses": [{"status": "complete", "translation_key": "status.disaggregation_status_complete", "count": 0, "percentage": 0.0}, {"status": "inprogress", "translation_key": "status.disaggregation_status_inprogress", "count": 0, "percentage": 0.0}, {"status": "notstarted", "translation_key": "status.disaggregation_status_notstarted", "count": 0, "percentage": 0.0}, {"status": "notapplicable", "translation_key": "status.disaggregation_status_notapplicable", "count": 11, "percentage": 100.0}], "totals": {"total": 11}}, {"sdg_goal": "3", "statuses": [{"status": "complete", "translation_key": "status.disaggregation_status_complete", "count": 0, "percentage": 0.0}, {"status": "inprogress", "translation_key": "status.disaggregation_status_inprogress", "count": 1, "percentage": 3.7037037037037037}, {"status": "notstarted", "translation_key": "status.disaggregation_status_notstarted", "count": 0, "percentage": 0.0}, {"status": "notapplicable", "translation_key": "status.disaggregation_status_notapplicable", "count": 26, "percentage": 96.29629629629629}], "totals": {"total": 27}}, {"sdg_goal": "16", "statuses": [{"status": "complete", "translation_key": "status.disaggregation_status_complete", "count": 2, "percentage": 8.695652173913043}, {"status": "inprogress", "translation_key": "status.disaggregation_status_inprogress", "count": 1, "percentage": 4.3478260869565215}, {"status": "notstarted", "translation_key": "status.disaggregation_status_notstarted", "count": 4, "percentage": 17.391304347826086}, {"status": "notapplicable", "translation_key": "status.disaggregation_status_notapplicable", "count": 16, "percentage": 69.56521739130434}], "totals": {"total": 23}}, {"sdg_goal": "4", "statuses": [{"status": "complete", "translation_key": "status.disaggregation_status_complete", "count": 5, "percentage": 45.45454545454545}, {"status": "inprogress", "translation_key": "status.disaggregation_status_inprogress", "count": 0, "percentage": 0.0}, {"status": "notstarted", "translation_key": "status.disaggregation_status_notstarted", "count": 2, "percentage": 18.181818181818183}, {"status": "notapplicable", "translation_key": "status.disaggregation_status_notapplicable", "count": 4, "percentage": 36.36363636363637}], "totals": {"total": 11}}, {"sdg_goal": "8", "statuses": [{"status": "complete", "translation_key": "status.disaggregation_status_complete", "count": 3, "percentage": 17.647058823529413}, {"status": "inprogress", "translation_key": "status.disaggregation_status_inprogress", "count": 1, "percentage": 5.882352941176471}, {"status": "notstarted", "translation_key": "status.disaggregation_status_notstarted", "count": 2, "percentage": 11.764705882352942}, {"status": "notapplicable", "translation_key": "status.disaggregation_status_notapplicable", "count": 11, "percentage": 64.70588235294117}], "totals": {"total": 17}}, {"sdg_goal": "9", "statuses": [{"status": "complete", "translation_key": "status.disaggregation_status_complete", "count": 1, "percentage": 8.333333333333334}, {"status": "inprogress", "translation_key": "status.disaggregation_status_inprogress", "count": 0, "percentage": 0.0}, {"status": "notstarted", "translation_key": "status.disaggregation_status_notstarted", "count": 1, "percentage": 8.333333333333334}, {"status": "notapplicable", "translation_key": "status.disaggregation_status_notapplicable", "count": 10, "percentage": 83.33333333333333}], "totals": {"total": 12}}, {"sdg_goal": "7", "statuses": [{"status": "complete", "translation_key": "status.disaggregation_status_complete", "count": 0, "percentage": 0.0}, {"status": "inprogress", "translation_key": "status.disaggregation_status_inprogress", "count": 0, "percentage": 0.0}, {"status": "notstarted", "translation_key": "status.disaggregation_status_notstarted", "count": 0, "percentage": 0.0}, {"status": "notapplicable", "translation_key": "status.disaggregation_status_notapplicable", "count": 6, "percentage": 100.0}], "totals": {"total": 6}}, {"sdg_goal": "15", "statuses": [{"status": "complete", "translation_key": "status.disaggregation_status_complete", "count": 0, "percentage": 0.0}, {"status": "inprogress", "translation_key": "status.disaggregation_status_inprogress", "count": 0, "percentage": 0.0}, {"status": "notstarted", "translation_key": "status.disaggregation_status_notstarted", "count": 1, "percentage": 7.142857142857143}, {"status": "notapplicable", "translation_key": "status.disaggregation_status_notapplicable", "count": 13, "percentage": 92.85714285714286}], "totals": {"total": 14}}, {"sdg_goal": "13", "statuses": [{"status": "complete", "translation_key": "status.disaggregation_status_complete", "count": 0, "percentage": 0.0}, {"status": "inprogress", "translation_key": "status.disaggregation_status_inprogress", "count": 0, "percentage": 0.0}, {"status": "notstarted", "translation_key": "status.disaggregation_status_notstarted", "count": 0, "percentage": 0.0}, {"status": "notapplicable", "translation_key": "status.disaggregation_status_notapplicable", "count": 8, "percentage": 100.0}], "totals": {"total": 8}}]}}