[{"Year":2010,"Value":40.3580152784,"Units":"Percentage (%)","GeoCode":null,"Observation status":"Normal value","Unit multiplier":"Units"},{"Year":2011,"Value":42.8948446578,"Units":"Percentage (%)","GeoCode":null,"Observation status":"Normal value","Unit multiplier":"Units"},{"Year":2012,"Value":43.8718054188,"Units":"Percentage (%)","GeoCode":null,"Observation status":"Normal value","Unit multiplier":"Units"},{"Year":2013,"Value":44.0757652333,"Units":"Percentage (%)","GeoCode":null,"Observation status":"Normal value","Unit multiplier":"Units"},{"Year":2014,"Value":44.8425979028,"Units":"Percentage (%)","GeoCode":null,"Observation status":"Normal value","Unit multiplier":"Units"},{"Year":2015,"Value":44.1016835447,"Units":"Percentage (%)","GeoCode":null,"Observation status":"Normal value","Unit multiplier":"Units"},{"Year":2016,"Value":44.5631777879,"Units":"Percentage (%)","GeoCode":null,"Observation status":"Normal value","Unit multiplier":"Units"},{"Year":2017,"Value":44.8434838401,"Units":"Percentage (%)","GeoCode":null,"Observation status":"Normal value","Unit multiplier":"Units"},{"Year":2018,"Value":44.2974195873,"Units":"Percentage (%)","GeoCode":null,"Observation status":"Normal value","Unit multiplier":"Units"},{"Year":2019,"Value":45.2323997057,"Units":"Percentage (%)","GeoCode":null,"Observation status":"Normal value","Unit multiplier":"Units"},{"Year":2020,"Value":43.5668219762,"Units":"Percentage (%)","GeoCode":null,"Observation status":"Normal value","Unit multiplier":"Units"}]