[{"Year":2000,"Value":65.15631434,"Units":"Percentage (%) of national budget","Observation status":"Undefined","Unit multiplier":"Units","Unit measure":"Percentage (%)"},{"Year":2001,"Value":66.19322177,"Units":"Percentage (%) of national budget","Observation status":"Undefined","Unit multiplier":"Units","Unit measure":"Percentage (%)"},{"Year":2002,"Value":66.95978205,"Units":"Percentage (%) of national budget","Observation status":"Undefined","Unit multiplier":"Units","Unit measure":"Percentage (%)"},{"Year":2003,"Value":66.01007118,"Units":"Percentage (%) of national budget","Observation status":"Undefined","Unit multiplier":"Units","Unit measure":"Percentage (%)"},{"Year":2004,"Value":65.6851937,"Units":"Percentage (%) of national budget","Observation status":"Undefined","Unit multiplier":"Units","Unit measure":"Percentage (%)"},{"Year":2005,"Value":65.22631225,"Units":"Percentage (%) of national budget","Observation status":"Undefined","Unit multiplier":"Units","Unit measure":"Percentage (%)"},{"Year":2006,"Value":64.85161006,"Units":"Percentage (%) of national budget","Observation status":"Undefined","Unit multiplier":"Units","Unit measure":"Percentage (%)"},{"Year":2007,"Value":64.77870305,"Units":"Percentage (%) of national budget","Observation status":"Undefined","Unit multiplier":"Units","Unit measure":"Percentage (%)"},{"Year":2008,"Value":62.37228481,"Units":"Percentage (%) of national budget","Observation status":"Undefined","Unit multiplier":"Units","Unit measure":"Percentage (%)"},{"Year":2009,"Value":65.31672344,"Units":"Percentage (%) of national budget","Observation status":"Undefined","Unit multiplier":"Units","Unit measure":"Percentage (%)"},{"Year":2010,"Value":65.24617464,"Units":"Percentage (%) of national budget","Observation status":"Undefined","Unit multiplier":"Units","Unit measure":"Percentage (%)"},{"Year":2011,"Value":65.47982703,"Units":"Percentage (%) of national budget","Observation status":"Undefined","Unit multiplier":"Units","Unit measure":"Percentage (%)"},{"Year":2012,"Value":65.78560864,"Units":"Percentage (%) of national budget","Observation status":"Undefined","Unit multiplier":"Units","Unit measure":"Percentage (%)"},{"Year":2013,"Value":66.64518237,"Units":"Percentage (%) of national budget","Observation status":"Undefined","Unit multiplier":"Units","Unit measure":"Percentage (%)"},{"Year":2014,"Value":67.38984609,"Units":"Percentage (%) of national budget","Observation status":"Undefined","Unit multiplier":"Units","Unit measure":"Percentage (%)"},{"Year":2015,"Value":68.13987609,"Units":"Percentage (%) of national budget","Observation status":"Undefined","Unit multiplier":"Units","Unit measure":"Percentage (%)"},{"Year":2000,"Value":17.19810667,"Units":"Percentage (%) of gross domestic product (GDP)","Observation status":"Undefined","Unit multiplier":"Units","Unit measure":"Percentage (%)"},{"Year":2001,"Value":18.19998747,"Units":"Percentage (%) of gross domestic product (GDP)","Observation status":"Undefined","Unit multiplier":"Units","Unit measure":"Percentage (%)"},{"Year":2002,"Value":19.3823553,"Units":"Percentage (%) of gross domestic product (GDP)","Observation status":"Undefined","Unit multiplier":"Units","Unit measure":"Percentage (%)"},{"Year":2003,"Value":20.19938049,"Units":"Percentage (%) of gross domestic product (GDP)","Observation status":"Undefined","Unit multiplier":"Units","Unit measure":"Percentage (%)"},{"Year":2004,"Value":21.25898225,"Units":"Percentage (%) of gross domestic product (GDP)","Observation status":"Undefined","Unit multiplier":"Units","Unit measure":"Percentage (%)"},{"Year":2005,"Value":21.92779266,"Units":"Percentage (%) of gross domestic product (GDP)","Observation status":"Undefined","Unit multiplier":"Units","Unit measure":"Percentage (%)"},{"Year":2006,"Value":22.60317812,"Units":"Percentage (%) of gross domestic product (GDP)","Observation status":"Undefined","Unit multiplier":"Units","Unit measure":"Percentage (%)"},{"Year":2007,"Value":23.27682002,"Units":"Percentage (%) of gross domestic product (GDP)","Observation status":"Undefined","Unit multiplier":"Units","Unit measure":"Percentage (%)"},{"Year":2008,"Value":25.04367671,"Units":"Percentage (%) of gross domestic product (GDP)","Observation status":"Undefined","Unit multiplier":"Units","Unit measure":"Percentage (%)"},{"Year":2009,"Value":28.3376781,"Units":"Percentage (%) of gross domestic product (GDP)","Observation status":"Undefined","Unit multiplier":"Units","Unit measure":"Percentage (%)"},{"Year":2010,"Value":28.91882251,"Units":"Percentage (%) of gross domestic product (GDP)","Observation status":"Undefined","Unit multiplier":"Units","Unit measure":"Percentage (%)"},{"Year":2011,"Value":28.63680448,"Units":"Percentage (%) of gross domestic product (GDP)","Observation status":"Undefined","Unit multiplier":"Units","Unit measure":"Percentage (%)"},{"Year":2012,"Value":29.09953406,"Units":"Percentage (%) of gross domestic product (GDP)","Observation status":"Undefined","Unit multiplier":"Units","Unit measure":"Percentage (%)"},{"Year":2013,"Value":28.92871702,"Units":"Percentage (%) of gross domestic product (GDP)","Observation status":"Undefined","Unit multiplier":"Units","Unit measure":"Percentage (%)"},{"Year":2014,"Value":29.06991488,"Units":"Percentage (%) of gross domestic product (GDP)","Observation status":"Undefined","Unit multiplier":"Units","Unit measure":"Percentage (%)"},{"Year":2015,"Value":28.9170488,"Units":"Percentage (%) of gross domestic product (GDP)","Observation status":"Undefined","Unit multiplier":"Units","Unit measure":"Percentage (%)"}]