[{"Year":"2000 Q1","Value":5.8,"Series":"Seasonally adjusted","GeoCode":null,"Observation status":"Normal value","Unit multiplier":"Units","Unit measure":"Percentage (%)"},{"Year":"2000 Q2","Value":5.5,"Series":"Seasonally adjusted","GeoCode":null,"Observation status":"Normal value","Unit multiplier":"Units","Unit measure":"Percentage (%)"},{"Year":"2000 Q3","Value":5.3,"Series":"Seasonally adjusted","GeoCode":null,"Observation status":"Normal value","Unit multiplier":"Units","Unit measure":"Percentage (%)"},{"Year":"2000 Q4","Value":5.2,"Series":"Seasonally adjusted","GeoCode":null,"Observation status":"Normal value","Unit multiplier":"Units","Unit measure":"Percentage (%)"},{"Year":"2001 Q1","Value":5.1,"Series":"Seasonally adjusted","GeoCode":null,"Observation status":"Normal value","Unit multiplier":"Units","Unit measure":"Percentage (%)"},{"Year":"2001 Q2","Value":5.0,"Series":"Seasonally adjusted","GeoCode":null,"Observation status":"Normal value","Unit multiplier":"Units","Unit measure":"Percentage (%)"},{"Year":"2001 Q3","Value":5.1,"Series":"Seasonally adjusted","GeoCode":null,"Observation status":"Normal value","Unit multiplier":"Units","Unit measure":"Percentage (%)"},{"Year":"2001 Q4","Value":5.2,"Series":"Seasonally adjusted","GeoCode":null,"Observation status":"Normal value","Unit multiplier":"Units","Unit measure":"Percentage (%)"},{"Year":"2002 Q1","Value":5.2,"Series":"Seasonally adjusted","GeoCode":null,"Observation status":"Normal value","Unit multiplier":"Units","Unit measure":"Percentage (%)"},{"Year":"2002 Q2","Value":5.2,"Series":"Seasonally adjusted","GeoCode":null,"Observation status":"Normal value","Unit multiplier":"Units","Unit measure":"Percentage (%)"},{"Year":"2002 Q3","Value":5.3,"Series":"Seasonally adjusted","GeoCode":null,"Observation status":"Normal value","Unit multiplier":"Units","Unit measure":"Percentage (%)"},{"Year":"2002 Q4","Value":5.1,"Series":"Seasonally adjusted","GeoCode":null,"Observation status":"Normal value","Unit multiplier":"Units","Unit measure":"Percentage (%)"},{"Year":"2003 Q1","Value":5.2,"Series":"Seasonally adjusted","GeoCode":null,"Observation status":"Normal value","Unit multiplier":"Units","Unit measure":"Percentage (%)"},{"Year":"2003 Q2","Value":4.9,"Series":"Seasonally adjusted","GeoCode":null,"Observation status":"Normal value","Unit multiplier":"Units","Unit measure":"Percentage (%)"},{"Year":"2003 Q3","Value":5.0,"Series":"Seasonally adjusted","GeoCode":null,"Observation status":"Normal value","Unit multiplier":"Units","Unit measure":"Percentage (%)"},{"Year":"2003 Q4","Value":4.9,"Series":"Seasonally adjusted","GeoCode":null,"Observation status":"Normal value","Unit multiplier":"Units","Unit measure":"Percentage (%)"},{"Year":"2004 Q1","Value":4.8,"Series":"Seasonally adjusted","GeoCode":null,"Observation status":"Normal value","Unit multiplier":"Units","Unit measure":"Percentage (%)"},{"Year":"2004 Q2","Value":4.8,"Series":"Seasonally adjusted","GeoCode":null,"Observation status":"Normal value","Unit multiplier":"Units","Unit measure":"Percentage (%)"},{"Year":"2004 Q3","Value":4.7,"Series":"Seasonally adjusted","GeoCode":null,"Observation status":"Normal value","Unit multiplier":"Units","Unit measure":"Percentage (%)"},{"Year":"2004 Q4","Value":4.7,"Series":"Seasonally adjusted","GeoCode":null,"Observation status":"Normal value","Unit multiplier":"Units","Unit measure":"Percentage (%)"},{"Year":"2005 Q1","Value":4.7,"Series":"Seasonally adjusted","GeoCode":null,"Observation status":"Normal value","Unit multiplier":"Units","Unit measure":"Percentage (%)"},{"Year":"2005 Q2","Value":4.8,"Series":"Seasonally adjusted","GeoCode":null,"Observation status":"Normal value","Unit multiplier":"Units","Unit measure":"Percentage (%)"},{"Year":"2005 Q3","Value":4.7,"Series":"Seasonally adjusted","GeoCode":null,"Observation status":"Normal value","Unit multiplier":"Units","Unit measure":"Percentage (%)"},{"Year":"2005 Q4","Value":5.1,"Series":"Seasonally adjusted","GeoCode":null,"Observation status":"Normal value","Unit multiplier":"Units","Unit measure":"Percentage (%)"},{"Year":"2006 Q1","Value":5.2,"Series":"Seasonally adjusted","GeoCode":null,"Observation status":"Normal value","Unit multiplier":"Units","Unit measure":"Percentage (%)"},{"Year":"2006 Q2","Value":5.5,"Series":"Seasonally adjusted","GeoCode":null,"Observation status":"Normal value","Unit multiplier":"Units","Unit measure":"Percentage (%)"},{"Year":"2006 Q3","Value":5.5,"Series":"Seasonally adjusted","GeoCode":null,"Observation status":"Normal value","Unit multiplier":"Units","Unit measure":"Percentage (%)"},{"Year":"2006 Q4","Value":5.5,"Series":"Seasonally adjusted","GeoCode":null,"Observation status":"Normal value","Unit multiplier":"Units","Unit measure":"Percentage (%)"},{"Year":"2007 Q1","Value":5.5,"Series":"Seasonally adjusted","GeoCode":null,"Observation status":"Normal value","Unit multiplier":"Units","Unit measure":"Percentage (%)"},{"Year":"2007 Q2","Value":5.4,"Series":"Seasonally adjusted","GeoCode":null,"Observation status":"Normal value","Unit multiplier":"Units","Unit measure":"Percentage (%)"},{"Year":"2007 Q3","Value":5.3,"Series":"Seasonally adjusted","GeoCode":null,"Observation status":"Normal value","Unit multiplier":"Units","Unit measure":"Percentage (%)"},{"Year":"2007 Q4","Value":5.2,"Series":"Seasonally adjusted","GeoCode":null,"Observation status":"Normal value","Unit multiplier":"Units","Unit measure":"Percentage (%)"},{"Year":"2008 Q1","Value":5.2,"Series":"Seasonally adjusted","GeoCode":null,"Observation status":"Normal value","Unit multiplier":"Units","Unit measure":"Percentage (%)"},{"Year":"2008 Q2","Value":5.4,"Series":"Seasonally adjusted","GeoCode":null,"Observation status":"Normal value","Unit multiplier":"Units","Unit measure":"Percentage (%)"},{"Year":"2008 Q3","Value":5.9,"Series":"Seasonally adjusted","GeoCode":null,"Observation status":"Normal value","Unit multiplier":"Units","Unit measure":"Percentage (%)"},{"Year":"2008 Q4","Value":6.4,"Series":"Seasonally adjusted","GeoCode":null,"Observation status":"Normal value","Unit multiplier":"Units","Unit measure":"Percentage (%)"},{"Year":"2009 Q1","Value":7.1,"Series":"Seasonally adjusted","GeoCode":null,"Observation status":"Normal value","Unit multiplier":"Units","Unit measure":"Percentage (%)"},{"Year":"2009 Q2","Value":7.8,"Series":"Seasonally adjusted","GeoCode":null,"Observation status":"Normal value","Unit multiplier":"Units","Unit measure":"Percentage (%)"},{"Year":"2009 Q3","Value":7.8,"Series":"Seasonally adjusted","GeoCode":null,"Observation status":"Normal value","Unit multiplier":"Units","Unit measure":"Percentage (%)"},{"Year":"2009 Q4","Value":7.8,"Series":"Seasonally adjusted","GeoCode":null,"Observation status":"Normal value","Unit multiplier":"Units","Unit measure":"Percentage (%)"},{"Year":"2010 Q1","Value":8.0,"Series":"Seasonally adjusted","GeoCode":null,"Observation status":"Normal value","Unit multiplier":"Units","Unit measure":"Percentage (%)"},{"Year":"2010 Q2","Value":7.9,"Series":"Seasonally adjusted","GeoCode":null,"Observation status":"Normal value","Unit multiplier":"Units","Unit measure":"Percentage (%)"},{"Year":"2010 Q3","Value":7.8,"Series":"Seasonally adjusted","GeoCode":null,"Observation status":"Normal value","Unit multiplier":"Units","Unit measure":"Percentage (%)"},{"Year":"2010 Q4","Value":7.9,"Series":"Seasonally adjusted","GeoCode":null,"Observation status":"Normal value","Unit multiplier":"Units","Unit measure":"Percentage (%)"},{"Year":"2011 Q1","Value":7.8,"Series":"Seasonally adjusted","GeoCode":null,"Observation status":"Normal value","Unit multiplier":"Units","Unit measure":"Percentage (%)"},{"Year":"2011 Q2","Value":7.9,"Series":"Seasonally adjusted","GeoCode":null,"Observation status":"Normal value","Unit multiplier":"Units","Unit measure":"Percentage (%)"},{"Year":"2011 Q3","Value":8.3,"Series":"Seasonally adjusted","GeoCode":null,"Observation status":"Normal value","Unit multiplier":"Units","Unit measure":"Percentage (%)"},{"Year":"2011 Q4","Value":8.4,"Series":"Seasonally adjusted","GeoCode":null,"Observation status":"Normal value","Unit multiplier":"Units","Unit measure":"Percentage (%)"},{"Year":"2012 Q1","Value":8.2,"Series":"Seasonally adjusted","GeoCode":null,"Observation status":"Normal value","Unit multiplier":"Units","Unit measure":"Percentage (%)"},{"Year":"2012 Q2","Value":8.0,"Series":"Seasonally adjusted","GeoCode":null,"Observation status":"Normal value","Unit multiplier":"Units","Unit measure":"Percentage (%)"},{"Year":"2012 Q3","Value":7.9,"Series":"Seasonally adjusted","GeoCode":null,"Observation status":"Normal value","Unit multiplier":"Units","Unit measure":"Percentage (%)"},{"Year":"2012 Q4","Value":7.8,"Series":"Seasonally adjusted","GeoCode":null,"Observation status":"Normal value","Unit multiplier":"Units","Unit measure":"Percentage (%)"},{"Year":"2013 Q1","Value":7.8,"Series":"Seasonally adjusted","GeoCode":null,"Observation status":"Normal value","Unit multiplier":"Units","Unit measure":"Percentage (%)"},{"Year":"2013 Q2","Value":7.7,"Series":"Seasonally adjusted","GeoCode":null,"Observation status":"Normal value","Unit multiplier":"Units","Unit measure":"Percentage (%)"},{"Year":"2013 Q3","Value":7.6,"Series":"Seasonally adjusted","GeoCode":null,"Observation status":"Normal value","Unit multiplier":"Units","Unit measure":"Percentage (%)"},{"Year":"2013 Q4","Value":7.2,"Series":"Seasonally adjusted","GeoCode":null,"Observation status":"Normal value","Unit multiplier":"Units","Unit measure":"Percentage (%)"},{"Year":"2014 Q1","Value":6.8,"Series":"Seasonally adjusted","GeoCode":null,"Observation status":"Normal value","Unit multiplier":"Units","Unit measure":"Percentage (%)"},{"Year":"2014 Q2","Value":6.3,"Series":"Seasonally adjusted","GeoCode":null,"Observation status":"Normal value","Unit multiplier":"Units","Unit measure":"Percentage (%)"},{"Year":"2014 Q3","Value":6.0,"Series":"Seasonally adjusted","GeoCode":null,"Observation status":"Normal value","Unit multiplier":"Units","Unit measure":"Percentage (%)"},{"Year":"2014 Q4","Value":5.7,"Series":"Seasonally adjusted","GeoCode":null,"Observation status":"Normal value","Unit multiplier":"Units","Unit measure":"Percentage (%)"},{"Year":"2015 Q1","Value":5.5,"Series":"Seasonally adjusted","GeoCode":null,"Observation status":"Normal value","Unit multiplier":"Units","Unit measure":"Percentage (%)"},{"Year":"2015 Q2","Value":5.6,"Series":"Seasonally adjusted","GeoCode":null,"Observation status":"Normal value","Unit multiplier":"Units","Unit measure":"Percentage (%)"},{"Year":"2015 Q3","Value":5.3,"Series":"Seasonally adjusted","GeoCode":null,"Observation status":"Normal value","Unit multiplier":"Units","Unit measure":"Percentage (%)"},{"Year":"2015 Q4","Value":5.1,"Series":"Seasonally adjusted","GeoCode":null,"Observation status":"Normal value","Unit multiplier":"Units","Unit measure":"Percentage (%)"},{"Year":"2016 Q1","Value":5.1,"Series":"Seasonally adjusted","GeoCode":null,"Observation status":"Normal value","Unit multiplier":"Units","Unit measure":"Percentage (%)"},{"Year":"2016 Q2","Value":4.9,"Series":"Seasonally adjusted","GeoCode":null,"Observation status":"Normal value","Unit multiplier":"Units","Unit measure":"Percentage (%)"},{"Year":"2016 Q3","Value":4.8,"Series":"Seasonally adjusted","GeoCode":null,"Observation status":"Normal value","Unit multiplier":"Units","Unit measure":"Percentage (%)"},{"Year":"2016 Q4","Value":4.7,"Series":"Seasonally adjusted","GeoCode":null,"Observation status":"Normal value","Unit multiplier":"Units","Unit measure":"Percentage (%)"},{"Year":"2017 Q1","Value":4.6,"Series":"Seasonally adjusted","GeoCode":null,"Observation status":"Normal value","Unit multiplier":"Units","Unit measure":"Percentage (%)"},{"Year":"2017 Q2","Value":4.4,"Series":"Seasonally adjusted","GeoCode":null,"Observation status":"Normal value","Unit multiplier":"Units","Unit measure":"Percentage (%)"},{"Year":"2017 Q3","Value":4.3,"Series":"Seasonally adjusted","GeoCode":null,"Observation status":"Normal value","Unit multiplier":"Units","Unit measure":"Percentage (%)"},{"Year":"2017 Q4","Value":4.4,"Series":"Seasonally adjusted","GeoCode":null,"Observation status":"Normal value","Unit multiplier":"Units","Unit measure":"Percentage (%)"},{"Year":"2018 Q1","Value":4.2,"Series":"Seasonally adjusted","GeoCode":null,"Observation status":"Normal value","Unit multiplier":"Units","Unit measure":"Percentage (%)"},{"Year":"2018 Q2","Value":4.0,"Series":"Seasonally adjusted","GeoCode":null,"Observation status":"Normal value","Unit multiplier":"Units","Unit measure":"Percentage (%)"},{"Year":"2018 Q3","Value":4.1,"Series":"Seasonally adjusted","GeoCode":null,"Observation status":"Normal value","Unit multiplier":"Units","Unit measure":"Percentage (%)"},{"Year":"2018 Q4","Value":4.0,"Series":"Seasonally adjusted","GeoCode":null,"Observation status":"Normal value","Unit multiplier":"Units","Unit measure":"Percentage (%)"},{"Year":"2019 Q1","Value":3.8,"Series":"Seasonally adjusted","GeoCode":null,"Observation status":"Normal value","Unit multiplier":"Units","Unit measure":"Percentage (%)"},{"Year":"2019 Q2","Value":3.9,"Series":"Seasonally adjusted","GeoCode":null,"Observation status":"Normal value","Unit multiplier":"Units","Unit measure":"Percentage (%)"},{"Year":"2019 Q3","Value":3.8,"Series":"Seasonally adjusted","GeoCode":null,"Observation status":"Normal value","Unit multiplier":"Units","Unit measure":"Percentage (%)"},{"Year":"2019 Q4","Value":3.8,"Series":"Seasonally adjusted","GeoCode":null,"Observation status":"Normal value","Unit multiplier":"Units","Unit measure":"Percentage (%)"},{"Year":"2020 Q1","Value":4.0,"Series":"Seasonally adjusted","GeoCode":null,"Observation status":"Normal value","Unit multiplier":"Units","Unit measure":"Percentage (%)"},{"Year":"2020 Q2","Value":4.1,"Series":"Seasonally adjusted","GeoCode":null,"Observation status":"Normal value","Unit multiplier":"Units","Unit measure":"Percentage (%)"},{"Year":"2020 Q3","Value":4.8,"Series":"Seasonally adjusted","GeoCode":null,"Observation status":"Normal value","Unit multiplier":"Units","Unit measure":"Percentage (%)"},{"Year":"2020 Q4","Value":5.2,"Series":"Seasonally adjusted","GeoCode":null,"Observation status":"Normal value","Unit multiplier":"Units","Unit measure":"Percentage (%)"},{"Year":"2021 Q1","Value":4.9,"Series":"Seasonally adjusted","GeoCode":null,"Observation status":"Normal value","Unit multiplier":"Units","Unit measure":"Percentage (%)"},{"Year":"2021 Q2","Value":4.7,"Series":"Seasonally adjusted","GeoCode":null,"Observation status":"Normal value","Unit multiplier":"Units","Unit measure":"Percentage (%)"},{"Year":"2000 Q1","Value":5.8453436572,"Series":"Not seasonally adjusted","GeoCode":null,"Observation status":"Normal value","Unit multiplier":"Units","Unit measure":"Percentage (%)"},{"Year":"2000 Q2","Value":5.382752037,"Series":"Not seasonally adjusted","GeoCode":null,"Observation status":"Normal value","Unit multiplier":"Units","Unit measure":"Percentage (%)"},{"Year":"2000 Q3","Value":5.5400012577,"Series":"Not seasonally adjusted","GeoCode":null,"Observation status":"Normal value","Unit multiplier":"Units","Unit measure":"Percentage (%)"},{"Year":"2000 Q4","Value":5.0663157872,"Series":"Not seasonally adjusted","GeoCode":null,"Observation status":"Normal value","Unit multiplier":"Units","Unit measure":"Percentage (%)"},{"Year":"2001 Q1","Value":5.1378063623,"Series":"Not seasonally adjusted","GeoCode":null,"Observation status":"Normal value","Unit multiplier":"Units","Unit measure":"Percentage (%)"},{"Year":"2001 Q2","Value":4.8955517751,"Series":"Not seasonally adjusted","GeoCode":null,"Observation status":"Normal value","Unit multiplier":"Units","Unit measure":"Percentage (%)"},{"Year":"2001 Q3","Value":5.3129158098,"Series":"Not seasonally adjusted","GeoCode":null,"Observation status":"Normal value","Unit multiplier":"Units","Unit measure":"Percentage (%)"},{"Year":"2001 Q4","Value":5.0416044494,"Series":"Not seasonally adjusted","GeoCode":null,"Observation status":"Normal value","Unit multiplier":"Units","Unit measure":"Percentage (%)"},{"Year":"2002 Q1","Value":5.204975822,"Series":"Not seasonally adjusted","GeoCode":null,"Observation status":"Normal value","Unit multiplier":"Units","Unit measure":"Percentage (%)"},{"Year":"2002 Q2","Value":5.0177815897,"Series":"Not seasonally adjusted","GeoCode":null,"Observation status":"Normal value","Unit multiplier":"Units","Unit measure":"Percentage (%)"},{"Year":"2002 Q3","Value":5.5220384671,"Series":"Not seasonally adjusted","GeoCode":null,"Observation status":"Normal value","Unit multiplier":"Units","Unit measure":"Percentage (%)"},{"Year":"2002 Q4","Value":4.9950346874,"Series":"Not seasonally adjusted","GeoCode":null,"Observation status":"Normal value","Unit multiplier":"Units","Unit measure":"Percentage (%)"},{"Year":"2003 Q1","Value":5.1845979715,"Series":"Not seasonally adjusted","GeoCode":null,"Observation status":"Normal value","Unit multiplier":"Units","Unit measure":"Percentage (%)"},{"Year":"2003 Q2","Value":4.8022531369,"Series":"Not seasonally adjusted","GeoCode":null,"Observation status":"Normal value","Unit multiplier":"Units","Unit measure":"Percentage (%)"},{"Year":"2003 Q3","Value":5.2593829008,"Series":"Not seasonally adjusted","GeoCode":null,"Observation status":"Normal value","Unit multiplier":"Units","Unit measure":"Percentage (%)"},{"Year":"2003 Q4","Value":4.7830810043,"Series":"Not seasonally adjusted","GeoCode":null,"Observation status":"Normal value","Unit multiplier":"Units","Unit measure":"Percentage (%)"},{"Year":"2004 Q1","Value":4.7992994192,"Series":"Not seasonally adjusted","GeoCode":null,"Observation status":"Normal value","Unit multiplier":"Units","Unit measure":"Percentage (%)"},{"Year":"2004 Q2","Value":4.6769485093,"Series":"Not seasonally adjusted","GeoCode":null,"Observation status":"Normal value","Unit multiplier":"Units","Unit measure":"Percentage (%)"},{"Year":"2004 Q3","Value":4.8980488127,"Series":"Not seasonally adjusted","GeoCode":null,"Observation status":"Normal value","Unit multiplier":"Units","Unit measure":"Percentage (%)"},{"Year":"2004 Q4","Value":4.6149101787,"Series":"Not seasonally adjusted","GeoCode":null,"Observation status":"Normal value","Unit multiplier":"Units","Unit measure":"Percentage (%)"},{"Year":"2005 Q1","Value":4.6795763283,"Series":"Not seasonally adjusted","GeoCode":null,"Observation status":"Normal value","Unit multiplier":"Units","Unit measure":"Percentage (%)"},{"Year":"2005 Q2","Value":4.6384209309,"Series":"Not seasonally adjusted","GeoCode":null,"Observation status":"Normal value","Unit multiplier":"Units","Unit measure":"Percentage (%)"},{"Year":"2005 Q3","Value":4.9497081839,"Series":"Not seasonally adjusted","GeoCode":null,"Observation status":"Normal value","Unit multiplier":"Units","Unit measure":"Percentage (%)"},{"Year":"2005 Q4","Value":5.0257958064,"Series":"Not seasonally adjusted","GeoCode":null,"Observation status":"Normal value","Unit multiplier":"Units","Unit measure":"Percentage (%)"},{"Year":"2006 Q1","Value":5.2223704363,"Series":"Not seasonally adjusted","GeoCode":null,"Observation status":"Normal value","Unit multiplier":"Units","Unit measure":"Percentage (%)"},{"Year":"2006 Q2","Value":5.3730360873,"Series":"Not seasonally adjusted","GeoCode":null,"Observation status":"Normal value","Unit multiplier":"Units","Unit measure":"Percentage (%)"},{"Year":"2006 Q3","Value":5.7031341531,"Series":"Not seasonally adjusted","GeoCode":null,"Observation status":"Normal value","Unit multiplier":"Units","Unit measure":"Percentage (%)"},{"Year":"2006 Q4","Value":5.3718510467,"Series":"Not seasonally adjusted","GeoCode":null,"Observation status":"Normal value","Unit multiplier":"Units","Unit measure":"Percentage (%)"},{"Year":"2007 Q1","Value":5.501779709,"Series":"Not seasonally adjusted","GeoCode":null,"Observation status":"Normal value","Unit multiplier":"Units","Unit measure":"Percentage (%)"},{"Year":"2007 Q2","Value":5.2587364329,"Series":"Not seasonally adjusted","GeoCode":null,"Observation status":"Normal value","Unit multiplier":"Units","Unit measure":"Percentage (%)"},{"Year":"2007 Q3","Value":5.5357266552,"Series":"Not seasonally adjusted","GeoCode":null,"Observation status":"Normal value","Unit multiplier":"Units","Unit measure":"Percentage (%)"},{"Year":"2007 Q4","Value":5.0203162979,"Series":"Not seasonally adjusted","GeoCode":null,"Observation status":"Normal value","Unit multiplier":"Units","Unit measure":"Percentage (%)"},{"Year":"2008 Q1","Value":5.1706487993,"Series":"Not seasonally adjusted","GeoCode":null,"Observation status":"Normal value","Unit multiplier":"Units","Unit measure":"Percentage (%)"},{"Year":"2008 Q2","Value":5.261448542,"Series":"Not seasonally adjusted","GeoCode":null,"Observation status":"Normal value","Unit multiplier":"Units","Unit measure":"Percentage (%)"},{"Year":"2008 Q3","Value":6.0836770882,"Series":"Not seasonally adjusted","GeoCode":null,"Observation status":"Normal value","Unit multiplier":"Units","Unit measure":"Percentage (%)"},{"Year":"2008 Q4","Value":6.2120632379,"Series":"Not seasonally adjusted","GeoCode":null,"Observation status":"Normal value","Unit multiplier":"Units","Unit measure":"Percentage (%)"},{"Year":"2009 Q1","Value":7.0628841963,"Series":"Not seasonally adjusted","GeoCode":null,"Observation status":"Normal value","Unit multiplier":"Units","Unit measure":"Percentage (%)"},{"Year":"2009 Q2","Value":7.6803638178,"Series":"Not seasonally adjusted","GeoCode":null,"Observation status":"Normal value","Unit multiplier":"Units","Unit measure":"Percentage (%)"},{"Year":"2009 Q3","Value":8.0684713778,"Series":"Not seasonally adjusted","GeoCode":null,"Observation status":"Normal value","Unit multiplier":"Units","Unit measure":"Percentage (%)"},{"Year":"2009 Q4","Value":7.6324986731,"Series":"Not seasonally adjusted","GeoCode":null,"Observation status":"Normal value","Unit multiplier":"Units","Unit measure":"Percentage (%)"},{"Year":"2010 Q1","Value":7.9984365464,"Series":"Not seasonally adjusted","GeoCode":null,"Observation status":"Normal value","Unit multiplier":"Units","Unit measure":"Percentage (%)"},{"Year":"2010 Q2","Value":7.7645726916,"Series":"Not seasonally adjusted","GeoCode":null,"Observation status":"Normal value","Unit multiplier":"Units","Unit measure":"Percentage (%)"},{"Year":"2010 Q3","Value":7.9754639524,"Series":"Not seasonally adjusted","GeoCode":null,"Observation status":"Normal value","Unit multiplier":"Units","Unit measure":"Percentage (%)"},{"Year":"2010 Q4","Value":7.7310549327,"Series":"Not seasonally adjusted","GeoCode":null,"Observation status":"Normal value","Unit multiplier":"Units","Unit measure":"Percentage (%)"},{"Year":"2011 Q1","Value":7.7609135096,"Series":"Not seasonally adjusted","GeoCode":null,"Observation status":"Normal value","Unit multiplier":"Units","Unit measure":"Percentage (%)"},{"Year":"2011 Q2","Value":7.8475718718,"Series":"Not seasonally adjusted","GeoCode":null,"Observation status":"Normal value","Unit multiplier":"Units","Unit measure":"Percentage (%)"},{"Year":"2011 Q3","Value":8.555846351,"Series":"Not seasonally adjusted","GeoCode":null,"Observation status":"Normal value","Unit multiplier":"Units","Unit measure":"Percentage (%)"},{"Year":"2011 Q4","Value":8.26039509,"Series":"Not seasonally adjusted","GeoCode":null,"Observation status":"Normal value","Unit multiplier":"Units","Unit measure":"Percentage (%)"},{"Year":"2012 Q1","Value":8.1852712998,"Series":"Not seasonally adjusted","GeoCode":null,"Observation status":"Normal value","Unit multiplier":"Units","Unit measure":"Percentage (%)"},{"Year":"2012 Q2","Value":7.9106042883,"Series":"Not seasonally adjusted","GeoCode":null,"Observation status":"Normal value","Unit multiplier":"Units","Unit measure":"Percentage (%)"},{"Year":"2012 Q3","Value":8.0866978784,"Series":"Not seasonally adjusted","GeoCode":null,"Observation status":"Normal value","Unit multiplier":"Units","Unit measure":"Percentage (%)"},{"Year":"2012 Q4","Value":7.6797397448,"Series":"Not seasonally adjusted","GeoCode":null,"Observation status":"Normal value","Unit multiplier":"Units","Unit measure":"Percentage (%)"},{"Year":"2013 Q1","Value":7.819149541,"Series":"Not seasonally adjusted","GeoCode":null,"Observation status":"Normal value","Unit multiplier":"Units","Unit measure":"Percentage (%)"},{"Year":"2013 Q2","Value":7.6703916949,"Series":"Not seasonally adjusted","GeoCode":null,"Observation status":"Normal value","Unit multiplier":"Units","Unit measure":"Percentage (%)"},{"Year":"2013 Q3","Value":7.8422834897,"Series":"Not seasonally adjusted","GeoCode":null,"Observation status":"Normal value","Unit multiplier":"Units","Unit measure":"Percentage (%)"},{"Year":"2013 Q4","Value":7.0828690408,"Series":"Not seasonally adjusted","GeoCode":null,"Observation status":"Normal value","Unit multiplier":"Units","Unit measure":"Percentage (%)"},{"Year":"2014 Q1","Value":6.729857695,"Series":"Not seasonally adjusted","GeoCode":null,"Observation status":"Normal value","Unit multiplier":"Units","Unit measure":"Percentage (%)"},{"Year":"2014 Q2","Value":6.217879847,"Series":"Not seasonally adjusted","GeoCode":null,"Observation status":"Normal value","Unit multiplier":"Units","Unit measure":"Percentage (%)"},{"Year":"2014 Q3","Value":6.2023832999,"Series":"Not seasonally adjusted","GeoCode":null,"Observation status":"Normal value","Unit multiplier":"Units","Unit measure":"Percentage (%)"},{"Year":"2014 Q4","Value":5.56381185,"Series":"Not seasonally adjusted","GeoCode":null,"Observation status":"Normal value","Unit multiplier":"Units","Unit measure":"Percentage (%)"},{"Year":"2015 Q1","Value":5.5191465694,"Series":"Not seasonally adjusted","GeoCode":null,"Observation status":"Normal value","Unit multiplier":"Units","Unit measure":"Percentage (%)"},{"Year":"2015 Q2","Value":5.5408306195,"Series":"Not seasonally adjusted","GeoCode":null,"Observation status":"Normal value","Unit multiplier":"Units","Unit measure":"Percentage (%)"},{"Year":"2015 Q3","Value":5.527324091,"Series":"Not seasonally adjusted","GeoCode":null,"Observation status":"Normal value","Unit multiplier":"Units","Unit measure":"Percentage (%)"},{"Year":"2015 Q4","Value":4.9484385196,"Series":"Not seasonally adjusted","GeoCode":null,"Observation status":"Normal value","Unit multiplier":"Units","Unit measure":"Percentage (%)"},{"Year":"2016 Q1","Value":5.060135646,"Series":"Not seasonally adjusted","GeoCode":null,"Observation status":"Normal value","Unit multiplier":"Units","Unit measure":"Percentage (%)"},{"Year":"2016 Q2","Value":4.8549375643,"Series":"Not seasonally adjusted","GeoCode":null,"Observation status":"Normal value","Unit multiplier":"Units","Unit measure":"Percentage (%)"},{"Year":"2016 Q3","Value":5.0366531476,"Series":"Not seasonally adjusted","GeoCode":null,"Observation status":"Normal value","Unit multiplier":"Units","Unit measure":"Percentage (%)"},{"Year":"2016 Q4","Value":4.6190919179,"Series":"Not seasonally adjusted","GeoCode":null,"Observation status":"Normal value","Unit multiplier":"Units","Unit measure":"Percentage (%)"},{"Year":"2017 Q1","Value":4.5607298533,"Series":"Not seasonally adjusted","GeoCode":null,"Observation status":"Normal value","Unit multiplier":"Units","Unit measure":"Percentage (%)"},{"Year":"2017 Q2","Value":4.3528198959,"Series":"Not seasonally adjusted","GeoCode":null,"Observation status":"Normal value","Unit multiplier":"Units","Unit measure":"Percentage (%)"},{"Year":"2017 Q3","Value":4.4588072052,"Series":"Not seasonally adjusted","GeoCode":null,"Observation status":"Normal value","Unit multiplier":"Units","Unit measure":"Percentage (%)"},{"Year":"2017 Q4","Value":4.2352694941,"Series":"Not seasonally adjusted","GeoCode":null,"Observation status":"Normal value","Unit multiplier":"Units","Unit measure":"Percentage (%)"},{"Year":"2018 Q1","Value":4.199255236,"Series":"Not seasonally adjusted","GeoCode":null,"Observation status":"Normal value","Unit multiplier":"Units","Unit measure":"Percentage (%)"},{"Year":"2018 Q2","Value":3.9589060142,"Series":"Not seasonally adjusted","GeoCode":null,"Observation status":"Normal value","Unit multiplier":"Units","Unit measure":"Percentage (%)"},{"Year":"2018 Q3","Value":4.2599911868,"Series":"Not seasonally adjusted","GeoCode":null,"Observation status":"Normal value","Unit multiplier":"Units","Unit measure":"Percentage (%)"},{"Year":"2018 Q4","Value":3.9051042591,"Series":"Not seasonally adjusted","GeoCode":null,"Observation status":"Normal value","Unit multiplier":"Units","Unit measure":"Percentage (%)"},{"Year":"2019 Q1","Value":3.8072387721,"Series":"Not seasonally adjusted","GeoCode":null,"Observation status":"Normal value","Unit multiplier":"Units","Unit measure":"Percentage (%)"},{"Year":"2019 Q2","Value":3.8062127026,"Series":"Not seasonally adjusted","GeoCode":null,"Observation status":"Normal value","Unit multiplier":"Units","Unit measure":"Percentage (%)"},{"Year":"2019 Q3","Value":4.0194156525,"Series":"Not seasonally adjusted","GeoCode":null,"Observation status":"Normal value","Unit multiplier":"Units","Unit measure":"Percentage (%)"},{"Year":"2019 Q4","Value":3.7012186616,"Series":"Not seasonally adjusted","GeoCode":null,"Observation status":"Normal value","Unit multiplier":"Units","Unit measure":"Percentage (%)"},{"Year":"2020 Q1","Value":3.9523471011,"Series":"Not seasonally adjusted","GeoCode":null,"Observation status":"Normal value","Unit multiplier":"Units","Unit measure":"Percentage (%)"},{"Year":"2020 Q2","Value":3.957660609,"Series":"Not seasonally adjusted","GeoCode":null,"Observation status":"Normal value","Unit multiplier":"Units","Unit measure":"Percentage (%)"},{"Year":"2020 Q3","Value":5.0750169311,"Series":"Not seasonally adjusted","GeoCode":null,"Observation status":"Normal value","Unit multiplier":"Units","Unit measure":"Percentage (%)"},{"Year":"2020 Q4","Value":5.2208346219,"Series":"Not seasonally adjusted","GeoCode":null,"Observation status":"Normal value","Unit multiplier":"Units","Unit measure":"Percentage (%)"},{"Year":"2021 Q1","Value":4.8356195539,"Series":"Not seasonally adjusted","GeoCode":null,"Observation status":"Normal value","Unit multiplier":"Units","Unit measure":"Percentage (%)"},{"Year":"2021 Q2","Value":4.5143583122,"Series":"Not seasonally adjusted","GeoCode":null,"Observation status":"Normal value","Unit multiplier":"Units","Unit measure":"Percentage (%)"}]