{
  "resources": [
    {
      "path": "data.csv",
      "name": "data",
      "profile": "tabular-data-resource",
      "scheme": "file",
      "format": "csv",
      "hashing": "md5",
      "encoding": "utf-8",
      "schema": {
        "fields": [
          {
            "name": "Year",
            "type": "integer",
            "title": "Year"
          },
          {
            "name": "Series",
            "type": "string",
            "constraints": {
              "enum": [
                "Liquid assets to short term liabilities (%)",
                "Net open position in foreign exchange to capital (%)",
                "Non-performing loans to total gross loans (%)",
                "Regulatory capital to assets (%)",
                "Regulatory Tier 1 capital to risk-weighted assets (%)",
                "Return on assets (%)",
                "Non-performing loans net of provisions to capital (%)",
                ""
              ]
            },
            "title": "Series"
          },
          {
            "name": "Observation status",
            "type": "string",
            "title": "Observation status"
          },
          {
            "name": "Unit multiplier",
            "type": "string",
            "title": "Unit multiplier"
          },
          {
            "name": "Units",
            "type": "string",
            "constraints": {
              "enum": [
                "Percentage (%)",
                ""
              ]
            },
            "title": "Units"
          },
          {
            "name": "Value",
            "type": "number",
            "title": "Value"
          }
        ]
      }
    }
  ],
  "profile": "data-package",
  "name": "10-5-1",
  "title": "Financial Soundness Indicators"
}